finam_trade_api/__init__.py
finam_trade_api/access/__init__.py
finam_trade_api/access/access_token.py
finam_trade_api/access/model.py
finam_trade_api/account/__init__.py
finam_trade_api/account/account.py
finam_trade_api/account/model.py
finam_trade_api/assets/__init__.py
finam_trade_api/assets/assets.py
finam_trade_api/assets/model.py
finam_trade_api/base_client/__init__.py
finam_trade_api/base_client/base.py
finam_trade_api/base_client/models.py
finam_trade_api/base_client/token_manager.py
finam_trade_api/client.py
finam_trade_api/exceptions.py
finam_trade_api/instruments/__init__.py
finam_trade_api/instruments/instruments.py
finam_trade_api/instruments/model.py
finam_trade_api/models.py
finam_trade_api/order/__init__.py
finam_trade_api/order/model.py
finam_trade_api/order/order.py
finam_trade_api/quotas/__init__.py
finam_trade_api/quotas/model.py
finam_trade_api/quotas/quotas.py
finam_trade_api-4.2.4.dist-info/LICENSE
finam_trade_api-4.2.4.dist-info/METADATA
finam_trade_api-4.2.4.dist-info/WHEEL
finam_trade_api-4.2.4.dist-info/RECORD
