Metadata-Version: 2.1
Name: finam-trade-api
Version: 4.2.4
Summary: Асинхронный REST-клиент для API Finam
License: GNU GPL v.3.0
Author: DBoyara
Author-email: boyarshin.den@yandex.ru
Requires-Python: >=3.11,<4.0
Classifier: License :: Other/Proprietary License
Classifier: Programming Language :: Python :: 3
Classifier: Programming Language :: Python :: 3.11
Classifier: Programming Language :: Python :: 3.12
Classifier: Programming Language :: Python :: 3.13
Requires-Dist: aiohttp (>=3.10.11,<4.0.0)
Requires-Dist: pydantic (>=2.8.2,<3.0.0)
